nasa_pace_data_reader/L1.py
nasa_pace_data_reader/L2.py
nasa_pace_data_reader/__init__.py
nasa_pace_data_reader/plot.py
nasa_pace_data_reader-0.0.5.0.dist-info/LICENSE
nasa_pace_data_reader-0.0.5.0.dist-info/METADATA
nasa_pace_data_reader-0.0.5.0.dist-info/WHEEL
nasa_pace_data_reader-0.0.5.0.dist-info/top_level.txt
nasa_pace_data_reader-0.0.5.0.dist-info/RECORD
