Metadata-Version: 2.1
Name: nasa_pace_data_reader
Version: 0.0.5.0
Summary: A package for reading NASA PACE data files.
Author-email: Anin Puthukkudy <aputhukkudy@umbc.edu>
Project-URL: Homepage, https://github.com/aninramesh/nasa-pace-data-reader
Project-URL: Issues, https://github.com/aninramesh/nasa-pace-data-reader/issues
Classifier: Programming Language :: Python :: 3
Classifier: License :: OSI Approved :: MIT License
Classifier: Operating System :: OS Independent
Requires-Python: >=3.10
License-File: LICENSE
Requires-Dist: matplotlib >=3.6
Requires-Dist: numpy >=1.21.2
Requires-Dist: netCDF4 >=1.5.7
Requires-Dist: notebook >=6.4.3
Requires-Dist: scipy >=1.7.1
Requires-Dist: cartopy >=0.19.0
